py2hackCraft/__init__.py
py2hackCraft/material.py
py2hackCraft/modules.py
py2hackcraft-0.1.0.dist-info/METADATA
py2hackcraft-0.1.0.dist-info/WHEEL
py2hackcraft-0.1.0.dist-info/top_level.txt
py2hackcraft-0.1.0.dist-info/RECORD
