Metadata-Version: 2.4
Name: py2hackCraft
Version: 0.1.0
Summary: Python client library for hackCraft2
Home-page: https://github.com/0x48lab/hackCraft2-python
Author: masafumi_t
Author-email: masafumi_t@0x48lab.com
Classifier: Programming Language :: Python :: 3
Classifier: License :: OSI Approved :: MIT License
Classifier: Operating System :: OS Independent
Requires-Python: >=3.7
Requires-Dist: websocket-client>=1.6.0
Dynamic: author
Dynamic: author-email
Dynamic: classifier
Dynamic: description
Dynamic: description-content-type
Dynamic: home-page
Dynamic: requires-dist
Dynamic: requires-python
Dynamic: summary
